create_browser_app/__init__.py
create_browser_app/main.py
create_browser_app/template_fetcher.py
create_browser_app/templates.py
create_browser_app-0.1.12.dist-info/METADATA
create_browser_app-0.1.12.dist-info/WHEEL
create_browser_app-0.1.12.dist-info/entry_points.txt
create_browser_app-0.1.12.dist-info/top_level.txt
create_browser_app-0.1.12.dist-info/RECORD
