Metadata-Version: 2.4
Name: create-browser-app
Version: 0.1.12
Summary: Start your Stagehand project with a single command
Requires-Python: >=3.10
Requires-Dist: stagehand
Requires-Dist: click>=8.0
Requires-Dist: rich>=13.0
Requires-Dist: inquirer>=3.0
Requires-Dist: requests>=2.25.0
